CA/__init__.py
CA/__main__.py
CA/ca.py
CA/cli.py
CA/constants.py
CA/models/certificate.py
CA/models/store.py
CA/models/store_base.py
CA/utils/jks.py
CA/utils/pkcs.py
CA/utils/serialization.py
certificate_authority-0.1.1.dist-info/METADATA
certificate_authority-0.1.1.dist-info/WHEEL
certificate_authority-0.1.1.dist-info/licenses/LICENSE
certificate_authority-0.1.1.dist-info/RECORD
