Metadata-Version: 2.4
Name: certificate-authority
Version: 0.1.1
Summary: A Python-based Certificate Authority for managing X.509 certificates
Project-URL: Homepage, https://github.com/paigeadelethompson/python-certificate-authority
Project-URL: Documentation, https://github.com/paigeadelethompson/python-certificate-authority#readme
Project-URL: Repository, https://github.com/paigeadelethompson/python-certificate-authority.git
Project-URL: Issues, https://github.com/paigeadelethompson/python-certificate-authority/issues
Author-email: Paige Thompson <paige@paige.bio>
License-Expression: MIT
License-File: LICENSE
Keywords: authority,certificate,pki,ssl,tls,x509
Classifier: Development Status :: 4 - Beta
Classifier: Intended Audience :: Developers
Classifier: License :: OSI Approved :: MIT License
Classifier: Programming Language :: Python :: 3
Classifier: Programming Language :: Python :: 3.9
Classifier: Programming Language :: Python :: 3.10
Classifier: Programming Language :: Python :: 3.11
Classifier: Programming Language :: Python :: 3.12
Classifier: Programming Language :: Python :: 3.13
Classifier: Topic :: Security :: Cryptography
Requires-Python: >=3.9
Requires-Dist: aiofiles>=23.2.1
Requires-Dist: asn1crypto>=1.5.1
Requires-Dist: click>=8.1.7
Requires-Dist: cryptography>=42.0.0
Requires-Dist: pyjks>=20.0.0
Provides-Extra: dev
Requires-Dist: black>=24.2.0; extra == 'dev'
Requires-Dist: flake8>=7.0.0; extra == 'dev'
Requires-Dist: isort>=5.13.2; extra == 'dev'
Requires-Dist: mypy>=1.8.0; extra == 'dev'
Requires-Dist: pylint>=3.0.3; extra == 'dev'
Provides-Extra: test
Requires-Dist: aiohttp>=3.9.3; extra == 'test'
Requires-Dist: pytest-asyncio>=0.23.5; extra == 'test'
Requires-Dist: pytest-cov>=4.1.0; extra == 'test'
Requires-Dist: pytest>=8.0.0; extra == 'test'
